garf/community/google/bid_manager/__init__.py
garf/community/google/bid_manager/api_clients.py
garf/community/google/bid_manager/exceptions.py
garf/community/google/bid_manager/query_editor.py
garf/community/google/bid_manager/report_fetcher.py
garf_bid_manager/__init__.py
garf_bid_manager/api_clients.py
garf_bid_manager/exceptions.py
garf_bid_manager/query_editor.py
garf_bid_manager/report_fetcher.py
garf_bid_manager-1.0.0.dist-info/METADATA
garf_bid_manager-1.0.0.dist-info/WHEEL
garf_bid_manager-1.0.0.dist-info/entry_points.txt
garf_bid_manager-1.0.0.dist-info/top_level.txt
garf_bid_manager-1.0.0.dist-info/RECORD
