Metadata-Version: 2.4
Name: garf-bid-manager
Version: 1.0.0
Summary: Garf implementation for Google Bid Manager API
Author-email: Andrei Markin <amarkin@google.com>, "Google Inc. (gTech gPS CSE team)" <no-reply@google.com>
License: Apache 2.0
Classifier: Development Status :: 2 - Pre-Alpha
Classifier: Programming Language :: Python
Requires-Python: >=3.9
Requires-Dist: garf-core
Requires-Dist: garf-io
Requires-Dist: google-api-python-client
Requires-Dist: google_auth_oauthlib
Requires-Dist: tenacity
